xyz_saas/__init__.py
xyz_saas/admin.py
xyz_saas/apis.py
xyz_saas/apps.py
xyz_saas/auth_backends.py
xyz_saas/choices.py
xyz_saas/filters.py
xyz_saas/helper.py
xyz_saas/middleware.py
xyz_saas/models.py
xyz_saas/permissions.py
xyz_saas/receivers.py
xyz_saas/serializers.py
xyz_saas/signals.py
xyz_saas/migrations/0001_initial.py
xyz_saas/migrations/0002_auto_20220617_0117.py
xyz_saas/migrations/__init__.py
xyz_saas-0.3.0.dist-info/METADATA
xyz_saas-0.3.0.dist-info/WHEEL
xyz_saas-0.3.0.dist-info/top_level.txt
xyz_saas-0.3.0.dist-info/RECORD
